sorting_package/__init__.py
sorting_package/bubble_sort.py
sorting_package/insertion_sort.py
sorting_package/quick_sort.py
sorting_package/selection_sort.py
sorting_for_web-0.1.dist-info/METADATA
sorting_for_web-0.1.dist-info/WHEEL
sorting_for_web-0.1.dist-info/top_level.txt
sorting_for_web-0.1.dist-info/RECORD
