Metadata-Version: 2.1
Name: sorting-for-web
Version: 0.1
Summary: 4 Sorting algorithms
Home-page: UNKNOWN
Author: Ignas M
Author-email: UNKNOWN
License: MIT
Platform: UNKNOWN
